LICENSE
README.md
setup.py
blaze_double_bot/__init__.py
blaze_double_bot/bot.py
blaze_double_bot.egg-info/PKG-INFO
blaze_double_bot.egg-info/SOURCES.txt
blaze_double_bot.egg-info/dependency_links.txt
blaze_double_bot.egg-info/requires.txt
blaze_double_bot.egg-info/top_level.txt