Metadata-Version: 2.1
Name: blaze_double_bot
Version: 0.1.2
Summary: This Python library automates the betting process on the Blaze Double
Author: Rafael de Oliveira Ribeiro
Author-email: ror74559@gmail.com
License: MIT License
License-File: LICENSE
Requires-Dist: undetected_chromedriver
Requires-Dist: selenium
Requires-Dist: requests
